Metadata-Version: 2.1
Name: bg-urequests
Version: 0.0.1
Summary: Basic MicroPython HTTP request library
Home-page: https://github.com/snebot-bg/urequests
Author: snebot
Author-email: snebot@bitgrup.com
License: UNKNOWN
Platform: UNKNOWN
Requires-Python: >=3.6
